pypihub/__init__.py
pypihub/database.py
pypihub/logger.py
pypihub/pypihub.py
pypihub/settings.py
pypihub-0.21.dist-info/LICENSE.md
pypihub-0.21.dist-info/METADATA
pypihub-0.21.dist-info/WHEEL
pypihub-0.21.dist-info/entry_points.txt
pypihub-0.21.dist-info/top_level.txt
pypihub-0.21.dist-info/RECORD
