Metadata-Version: 2.1
Name: pypihub
Version: 0.21
Summary: Local PyPI Server with caching and upload support
Home-page: https://github.com/cumulus13/pypihub_flask
Author: Hadi Cahyadi
Author-email: cumulus13@gmail.com
License: LGPL-3.0-or-later
Classifier: Development Status :: 4 - Beta
Classifier: Environment :: Console
Classifier: Intended Audience :: Developers
Classifier: License :: OSI Approved :: GNU Lesser General Public License v3 (LGPLv3)
Classifier: Programming Language :: Python :: 3
Classifier: Operating System :: OS Independent
Classifier: Topic :: Software Development :: Libraries
Classifier: Topic :: Internet :: WWW/HTTP :: Indexing/Search
Requires-Python: >=3.7
License-File: LICENSE.md
Requires-Dist: requests
Requires-Dist: beautifulsoup4
Requires-Dist: pydebugger
Requires-Dist: rich
Requires-Dist: rich-argparse
Requires-Dist: configset
Provides-Extra: bcrypt
Requires-Dist: bcrypt ; extra == 'bcrypt'
Provides-Extra: flask
Requires-Dist: Flask ; extra == 'flask'
Provides-Extra: mysql
Requires-Dist: SQLAlchemy ; extra == 'mysql'
Requires-Dist: mysqlclient ; extra == 'mysql'
Provides-Extra: postgres
Requires-Dist: SQLAlchemy ; extra == 'postgres'
Requires-Dist: psycopg2 ; extra == 'postgres'
